{
    "useCustomTheme": true,
    "TitleFore": "#282a36",
    "TitleBack": "#bd93f9",
    "TitleInfo": "#808080",
    "NormalTitle": "#bd93f9",
    "DimmedTitle": "#808080",
    "SelectedTitle": "#ff79c6",
    "NormalDesc": "#808080",
    "DimmedDesc": "#808080",
    "SelectedDesc": "#ff79c6",
    "StatusMsg": "#50fa7b",
    "PinIndicatorColor": "#ffd700",
    "SelectedBorder": "#ff79c6",
    "SelectedDescBorder": "#ff79c6",
    "FilteredMatch": "#ffffff",
    "FilterPrompt": "#bd93f9",
    "FilterInfo": "#808080",
    "FilterText": "#ffffff",
    "FilterCursor": "#ffd700",
    "HelpKey": "#ffd700",
    "HelpDesc": "#808080",
    "PageActiveDot": "#ffd700",
    "PageInactiveDot": "#808080",
    "DividerDot": "#282a36",
    "PreviewedText": "#ffffff",
    "PreviewBorder": "#bd93f9"
}